quartet_trail/__init__.py
quartet_trail/apps.py
quartet_trail/models.py
quartet_trail/serializers.py
quartet_trail/signals.py
quartet_trail/urls.py
quartet_trail/views.py
quartet_trail/migrations/0001_initial.py
quartet_trail/migrations/0002_historicalfilter_historicalrulefilter.py
quartet_trail/migrations/0003_auto_20181225_1757.py
quartet_trail/migrations/0004_auto_20190107_1107.py
quartet_trail/migrations/0005_auto_20190128_1552.py
quartet_trail/migrations/0006_auto_20190214_1807.py
quartet_trail/migrations/0007_auto_20190305_2241.py
quartet_trail/migrations/0008_historicaltradeitem_serial_number_length.py
quartet_trail/migrations/0009_historicaltradeitem_pack_count.py
quartet_trail/migrations/0010_auto_20190613_2030.py
quartet_trail/migrations/0011_auto_20190828_1540.py
quartet_trail/migrations/0012_historicaltradeitem_package_uom.py
quartet_trail/migrations/0013_auto_20191219_1603.py
quartet_trail/migrations/0014_auto_20191219_1759.py
quartet_trail/migrations/0015_historicaloutboundmapping.py
quartet_trail/migrations/0016_auto_20200221_1042.py
quartet_trail/migrations/0017_auto_20200401_2145.py
quartet_trail/migrations/0018_auto_20200824_1624.py
quartet_trail/migrations/0019_auto_20200929_2130.py
quartet_trail/migrations/0020_auto_20210818_1612.py
quartet_trail/migrations/0021_alter_historicalauthenticationinfo_options_and_more.py
quartet_trail/migrations/__init__.py
quartet_trail-2.1.5.dist-info/AUTHORS.rst
quartet_trail-2.1.5.dist-info/LICENSE
quartet_trail-2.1.5.dist-info/METADATA
quartet_trail-2.1.5.dist-info/WHEEL
quartet_trail-2.1.5.dist-info/top_level.txt
quartet_trail-2.1.5.dist-info/RECORD
