Metadata-Version: 2.1
Name: quartet-trail
Version: 2.1.5
Summary: Logs action in Quartet
Home-page: https://gitlab.com/serial-lab/quartet-trail
Author: SerialLab
Author-email: slab@serial-lab.com
License: GPLv3
Keywords: quartet-trail
Platform: UNKNOWN
Classifier: Development Status :: 3 - Alpha
Classifier: Framework :: Django
Classifier: Framework :: Django :: 1.8
Classifier: Framework :: Django :: 1.9
Classifier: Framework :: Django :: 1.10
Classifier: Intended Audience :: Developers
Classifier: License :: OSI Approved :: GNU General Public License v3 (GPLv3)
Classifier: Natural Language :: English
Classifier: Programming Language :: Python :: 3.3
Classifier: Programming Language :: Python :: 3.4
Classifier: Programming Language :: Python :: 3.5
Requires-Dist: django-model-utils (>=2.0)
